flux_kontext_mcp/__init__.py
flux_kontext_mcp/__main__.py
flux_kontext_mcp/server.py
flux_kontext_mcp-0.0.4.dist-info/METADATA
flux_kontext_mcp-0.0.4.dist-info/WHEEL
flux_kontext_mcp-0.0.4.dist-info/entry_points.txt
flux_kontext_mcp-0.0.4.dist-info/licenses/LICENSE
flux_kontext_mcp-0.0.4.dist-info/RECORD
